[{"electro": {"min": null, "max": null, "limit": null, "actual": null, "prev": null, "sum": null}, "voda": {"actual": null, "prev": null, "tarif": null, "sum": null}, "gaz": {"isLich": false, "actual": null, "prev": null, "tarif": null, "transit": null, "sum": null}, "dom": {"actual": null}, "date": "test", "allSum": null}, {"electro": {"actual": 32875.0, "sum": "test"}, "voda": {"actual": 640.0, "sum": "test"}, "gaz": {"actual": 1.0, "isLich": false, "sum": "test"}, "dom": {"actual": "test"}, "date": "18-09-2022", "allSum": "test"}, {"electro": {"actual": 32875.0, "sum": "test"}, "voda": {"actual": 640.0, "sum": "test"}, "gaz": {"actual": 1.0, "isLich": false, "sum": "test"}, "dom": {"actual": "test"}, "date": "19-09-2022", "allSum": "test"}, {"electro": {"actual": 32875.0, "sum": "test"}, "voda": {"actual": 640.0, "sum": "test"}, "gaz": {"actual": 1, "isLich": false, "sum": "test"}, "dom": {"actual": "test"}, "date": "21-09-2022", "allSum": "test"}]